keyrock_template/__init__.py
keyrock_template/template/__init__.py
keyrock_template/template/exc.py
keyrock_template/template/template.py
keyrock_template/template/test_template.py
keyrock_template-2022.12.26.2203.dist-info/METADATA
keyrock_template-2022.12.26.2203.dist-info/WHEEL
keyrock_template-2022.12.26.2203.dist-info/top_level.txt
keyrock_template-2022.12.26.2203.dist-info/RECORD
