Metadata-Version: 2.1
Name: keyrock-template
Version: 2022.12.26.2203
Requires-Dist: keyrock-core
Requires-Dist: jinja2
